<?xml version="1.0"?>
<property-set xmlns="http://mcc.lip6.fr/">
   <property>
      <id>CircadianClock-PT-000001-CTLFireability-00</id>
      <description>Automatically generated by Citili v2022</description>
      <formula>
         <exists-path>
            <finally>
               <disjunction>
                  <conjunction>
                     <is-fireable>
                        <transition>bind_a</transition>
                     </is-fireable>
                     <exists-path>
                        <next>
                           <disjunction>
                              <disjunction>
                                 <conjunction>
                                    <is-fireable>
                                       <transition>transc_dr_a</transition>
                                    </is-fireable>
                                    <is-fireable>
                                       <transition>deactive</transition>
                                    </is-fireable>
                                 </conjunction>
                                 <negation>
                                    <is-fireable>
                                       <transition>transl_a</transition>
                                    </is-fireable>
                                 </negation>
                              </disjunction>
                              <is-fireable>
                                 <transition>rel_a</transition>
                              </is-fireable>
                           </disjunction>
                        </next>
                     </exists-path>
                  </conjunction>
                  <conjunction>
                     <conjunction>
                        <disjunction>
                           <conjunction>
                              <negation>
                                 <is-fireable>
                                    <transition>deg_r</transition>
                                 </is-fireable>
                              </negation>
                              <exists-path>
                                 <next>
                                    <is-fireable>
                                       <transition>bind_r</transition>
                                    </is-fireable>
                                 </next>
                              </exists-path>
                           </conjunction>
                           <disjunction>
                              <negation>
                                 <negation>
                                    <is-fireable>
                                       <transition>bind_a</transition>
                                    </is-fireable>
                                 </negation>
                              </negation>
                              <is-fireable>
                                 <transition>transl_a</transition>
                              </is-fireable>
                           </disjunction>
                        </disjunction>
                        <negation>
                           <disjunction>
                              <is-fireable>
                                 <transition>deg_ma</transition>
                              </is-fireable>
                              <exists-path>
                                 <finally>
                                    <is-fireable>
                                       <transition>deg_ma</transition>
                                    </is-fireable>
                                 </finally>
                              </exists-path>
                           </disjunction>
                        </negation>
                     </conjunction>
                     <exists-path>
                        <finally>
                           <negation>
                              <conjunction>
                                 <conjunction>
                                    <is-fireable>
                                       <transition>transc_da_a</transition>
                                    </is-fireable>
                                    <is-fireable>
                                       <transition>rel_a</transition>
                                    </is-fireable>
                                 </conjunction>
                                 <exists-path>
                                    <next>
                                       <is-fireable>
                                          <transition>transc_da</transition>
                                       </is-fireable>
                                    </next>
                                 </exists-path>
                              </conjunction>
                           </negation>
                        </finally>
                     </exists-path>
                  </conjunction>
               </disjunction>
            </finally>
         </exists-path>
      </formula>
   </property>
   <property>
      <id>CircadianClock-PT-000001-CTLFireability-01</id>
      <description>Automatically generated by Citili v2022</description>
      <formula>
         <all-paths>
            <globally>
               <negation>
                  <disjunction>
                     <all-paths>
                        <next>
                           <all-paths>
                              <next>
                                 <negation>
                                    <is-fireable>
                                       <transition>transl_r</transition>
                                    </is-fireable>
                                 </negation>
                              </next>
                           </all-paths>
                        </next>
                     </all-paths>
                     <exists-path>
                        <globally>
                           <all-paths>
                              <next>
                                 <all-paths>
                                    <until>
                                       <before>
                                          <is-fireable>
                                             <transition>transc_dr_a</transition>
                                          </is-fireable>
                                       </before>
                                       <reach>
                                          <is-fireable>
                                             <transition>bind_r</transition>
                                          </is-fireable>
                                       </reach>
                                    </until>
                                 </all-paths>
                              </next>
                           </all-paths>
                        </globally>
                     </exists-path>
                  </disjunction>
               </negation>
            </globally>
         </all-paths>
      </formula>
   </property>
   <property>
      <id>CircadianClock-PT-000001-CTLFireability-02</id>
      <description>Automatically generated by Citili v2022</description>
      <formula>
         <negation>
            <exists-path>
               <until>
                  <before>
                     <all-paths>
                        <globally>
                           <conjunction>
                              <exists-path>
                                 <until>
                                    <before>
                                       <all-paths>
                                          <globally>
                                             <is-fireable>
                                                <transition>rel_r</transition>
                                             </is-fireable>
                                          </globally>
                                       </all-paths>
                                    </before>
                                    <reach>
                                       <disjunction>
                                          <is-fireable>
                                             <transition>bind_a</transition>
                                          </is-fireable>
                                          <is-fireable>
                                             <transition>transc_da_a</transition>
                                          </is-fireable>
                                       </disjunction>
                                    </reach>
                                 </until>
                              </exists-path>
                              <exists-path>
                                 <next>
                                    <conjunction>
                                       <is-fireable>
                                          <transition>bind_a</transition>
                                       </is-fireable>
                                       <is-fireable>
                                          <transition>deg_mr</transition>
                                       </is-fireable>
                                    </conjunction>
                                 </next>
                              </exists-path>
                           </conjunction>
                        </globally>
                     </all-paths>
                  </before>
                  <reach>
                     <conjunction>
                        <is-fireable>
                           <transition>bind_r</transition>
                        </is-fireable>
                        <all-paths>
                           <until>
                              <before>
                                 <negation>
                                    <negation>
                                       <negation>
                                          <is-fireable>
                                             <transition>deg_a</transition>
                                          </is-fireable>
                                       </negation>
                                    </negation>
                                 </negation>
                              </before>
                              <reach>
                                 <is-fireable>
                                    <transition>transl_a</transition>
                                 </is-fireable>
                              </reach>
                           </until>
                        </all-paths>
                     </conjunction>
                  </reach>
               </until>
            </exists-path>
         </negation>
      </formula>
   </property>
   <property>
      <id>CircadianClock-PT-000001-CTLFireability-03</id>
      <description>Automatically generated by Citili v2022</description>
      <formula>
         <all-paths>
            <until>
               <before>
                  <all-paths>
                     <next>
                        <is-fireable>
                           <transition>rel_r</transition>
                        </is-fireable>
                     </next>
                  </all-paths>
               </before>
               <reach>
                  <is-fireable>
                     <transition>transc_dr_a</transition>
                  </is-fireable>
               </reach>
            </until>
         </all-paths>
      </formula>
   </property>
   <property>
      <id>CircadianClock-PT-000001-CTLFireability-04</id>
      <description>Automatically generated by Citili v2022</description>
      <formula>
         <conjunction>
            <negation>
               <exists-path>
                  <globally>
                     <negation>
                        <exists-path>
                           <finally>
                              <disjunction>
                                 <is-fireable>
                                    <transition>deactive</transition>
                                 </is-fireable>
                                 <disjunction>
                                    <is-fireable>
                                       <transition>deactive</transition>
                                    </is-fireable>
                                    <is-fireable>
                                       <transition>rel_r</transition>
                                    </is-fireable>
                                 </disjunction>
                              </disjunction>
                           </finally>
                        </exists-path>
                     </negation>
                  </globally>
               </exists-path>
            </negation>
            <all-paths>
               <globally>
                  <disjunction>
                     <conjunction>
                        <is-fireable>
                           <transition>deg_mr</transition>
                        </is-fireable>
                        <disjunction>
                           <conjunction>
                              <conjunction>
                                 <is-fireable>
                                    <transition>transl_r</transition>
                                 </is-fireable>
                                 <disjunction>
                                    <is-fireable>
                                       <transition>transl_r</transition>
                                    </is-fireable>
                                    <is-fireable>
                                       <transition>transc_dr</transition>
                                    </is-fireable>
                                 </disjunction>
                              </conjunction>
                              <exists-path>
                                 <globally>
                                    <is-fireable>
                                       <transition>deg_r</transition>
                                    </is-fireable>
                                 </globally>
                              </exists-path>
                           </conjunction>
                           <is-fireable>
                              <transition>deg_r</transition>
                           </is-fireable>
                        </disjunction>
                     </conjunction>
                     <disjunction>
                        <disjunction>
                           <is-fireable>
                              <transition>rel_r</transition>
                           </is-fireable>
                           <disjunction>
                              <negation>
                                 <disjunction>
                                    <is-fireable>
                                       <transition>bind_r</transition>
                                    </is-fireable>
                                    <is-fireable>
                                       <transition>transc_da_a</transition>
                                    </is-fireable>
                                 </disjunction>
                              </negation>
                              <negation>
                                 <exists-path>
                                    <finally>
                                       <is-fireable>
                                          <transition>transc_dr</transition>
                                       </is-fireable>
                                    </finally>
                                 </exists-path>
                              </negation>
                           </disjunction>
                        </disjunction>
                        <conjunction>
                           <is-fireable>
                              <transition>transc_da_a</transition>
                           </is-fireable>
                           <negation>
                              <negation>
                                 <disjunction>
                                    <is-fireable>
                                       <transition>transc_da</transition>
                                    </is-fireable>
                                    <is-fireable>
                                       <transition>deg_ma</transition>
                                    </is-fireable>
                                 </disjunction>
                              </negation>
                           </negation>
                        </conjunction>
                     </disjunction>
                  </disjunction>
               </globally>
            </all-paths>
         </conjunction>
      </formula>
   </property>
   <property>
      <id>CircadianClock-PT-000001-CTLFireability-05</id>
      <description>Automatically generated by Citili v2022</description>
      <formula>
         <exists-path>
            <next>
               <disjunction>
                  <conjunction>
                     <exists-path>
                        <until>
                           <before>
                              <all-paths>
                                 <next>
                                    <negation>
                                       <is-fireable>
                                          <transition>deg_c</transition>
                                       </is-fireable>
                                    </negation>
                                 </next>
                              </all-paths>
                           </before>
                           <reach>
                              <disjunction>
                                 <negation>
                                    <disjunction>
                                       <is-fireable>
                                          <transition>transc_dr</transition>
                                       </is-fireable>
                                       <is-fireable>
                                          <transition>deg_mr</transition>
                                       </is-fireable>
                                    </disjunction>
                                 </negation>
                                 <exists-path>
                                    <globally>
                                       <is-fireable>
                                          <transition>bind_r</transition>
                                       </is-fireable>
                                    </globally>
                                 </exists-path>
                              </disjunction>
                           </reach>
                        </until>
                     </exists-path>
                     <exists-path>
                        <until>
                           <before>
                              <negation>
                                 <is-fireable>
                                    <transition>deg_c</transition>
                                 </is-fireable>
                              </negation>
                           </before>
                           <reach>
                              <conjunction>
                                 <all-paths>
                                    <finally>
                                       <is-fireable>
                                          <transition>deg_c</transition>
                                       </is-fireable>
                                    </finally>
                                 </all-paths>
                                 <negation>
                                    <exists-path>
                                       <globally>
                                          <is-fireable>
                                             <transition>transc_da</transition>
                                          </is-fireable>
                                       </globally>
                                    </exists-path>
                                 </negation>
                              </conjunction>
                           </reach>
                        </until>
                     </exists-path>
                  </conjunction>
                  <all-paths>
                     <until>
                        <before>
                           <negation>
                              <exists-path>
                                 <until>
                                    <before>
                                       <all-paths>
                                          <finally>
                                             <is-fireable>
                                                <transition>deg_ma</transition>
                                             </is-fireable>
                                          </finally>
                                       </all-paths>
                                    </before>
                                    <reach>
                                       <conjunction>
                                          <is-fireable>
                                             <transition>deg_ma</transition>
                                          </is-fireable>
                                          <is-fireable>
                                             <transition>transl_r</transition>
                                          </is-fireable>
                                       </conjunction>
                                    </reach>
                                 </until>
                              </exists-path>
                           </negation>
                        </before>
                        <reach>
                           <conjunction>
                              <disjunction>
                                 <is-fireable>
                                    <transition>transc_da_a</transition>
                                 </is-fireable>
                                 <all-paths>
                                    <finally>
                                       <is-fireable>
                                          <transition>rel_a</transition>
                                       </is-fireable>
                                    </finally>
                                 </all-paths>
                              </disjunction>
                              <all-paths>
                                 <finally>
                                    <negation>
                                       <is-fireable>
                                          <transition>transc_da</transition>
                                       </is-fireable>
                                    </negation>
                                 </finally>
                              </all-paths>
                           </conjunction>
                        </reach>
                     </until>
                  </all-paths>
               </disjunction>
            </next>
         </exists-path>
      </formula>
   </property>
   <property>
      <id>CircadianClock-PT-000001-CTLFireability-06</id>
      <description>Automatically generated by Citili v2022</description>
      <formula>
         <negation>
            <exists-path>
               <until>
                  <before>
                     <disjunction>
                        <all-paths>
                           <until>
                              <before>
                                 <disjunction>
                                    <negation>
                                       <conjunction>
                                          <is-fireable>
                                             <transition>bind_r</transition>
                                          </is-fireable>
                                          <is-fireable>
                                             <transition>bind_a</transition>
                                          </is-fireable>
                                       </conjunction>
                                    </negation>
                                    <all-paths>
                                       <finally>
                                          <is-fireable>
                                             <transition>transl_a</transition>
                                          </is-fireable>
                                       </finally>
                                    </all-paths>
                                 </disjunction>
                              </before>
                              <reach>
                                 <exists-path>
                                    <finally>
                                       <conjunction>
                                          <is-fireable>
                                             <transition>transc_dr_a</transition>
                                          </is-fireable>
                                          <is-fireable>
                                             <transition>deg_c</transition>
                                          </is-fireable>
                                       </conjunction>
                                    </finally>
                                 </exists-path>
                              </reach>
                           </until>
                        </all-paths>
                        <is-fireable>
                           <transition>deg_r</transition>
                        </is-fireable>
                     </disjunction>
                  </before>
                  <reach>
                     <negation>
                        <all-paths>
                           <globally>
                              <is-fireable>
                                 <transition>transl_r</transition>
                              </is-fireable>
                           </globally>
                        </all-paths>
                     </negation>
                  </reach>
               </until>
            </exists-path>
         </negation>
      </formula>
   </property>
   <property>
      <id>CircadianClock-PT-000001-CTLFireability-07</id>
      <description>Automatically generated by Citili v2022</description>
      <formula>
         <all-paths>
            <finally>
               <exists-path>
                  <next>
                     <all-paths>
                        <until>
                           <before>
                              <is-fireable>
                                 <transition>bind_a</transition>
                              </is-fireable>
                           </before>
                           <reach>
                              <exists-path>
                                 <finally>
                                    <negation>
                                       <is-fireable>
                                          <transition>transc_dr</transition>
                                       </is-fireable>
                                    </negation>
                                 </finally>
                              </exists-path>
                           </reach>
                        </until>
                     </all-paths>
                  </next>
               </exists-path>
            </finally>
         </all-paths>
      </formula>
   </property>
   <property>
      <id>CircadianClock-PT-000001-CTLFireability-08</id>
      <description>Automatically generated by Citili v2022</description>
      <formula>
         <exists-path>
            <next>
               <is-fireable>
                  <transition>transl_r</transition>
               </is-fireable>
            </next>
         </exists-path>
      </formula>
   </property>
   <property>
      <id>CircadianClock-PT-000001-CTLFireability-09</id>
      <description>Automatically generated by Citili v2022</description>
      <formula>
         <exists-path>
            <finally>
               <exists-path>
                  <globally>
                     <negation>
                        <all-paths>
                           <until>
                              <before>
                                 <exists-path>
                                    <until>
                                       <before>
                                          <is-fireable>
                                             <transition>rel_r</transition>
                                          </is-fireable>
                                       </before>
                                       <reach>
                                          <is-fireable>
                                             <transition>deg_mr</transition>
                                          </is-fireable>
                                       </reach>
                                    </until>
                                 </exists-path>
                              </before>
                              <reach>
                                 <all-paths>
                                    <next>
                                       <is-fireable>
                                          <transition>bind_r</transition>
                                       </is-fireable>
                                    </next>
                                 </all-paths>
                              </reach>
                           </until>
                        </all-paths>
                     </negation>
                  </globally>
               </exists-path>
            </finally>
         </exists-path>
      </formula>
   </property>
   <property>
      <id>CircadianClock-PT-000001-CTLFireability-10</id>
      <description>Automatically generated by Citili v2022</description>
      <formula>
         <disjunction>
            <exists-path>
               <next>
                  <conjunction>
                     <conjunction>
                        <conjunction>
                           <all-paths>
                              <globally>
                                 <conjunction>
                                    <is-fireable>
                                       <transition>transc_da_a</transition>
                                    </is-fireable>
                                    <is-fireable>
                                       <transition>bind_r</transition>
                                    </is-fireable>
                                 </conjunction>
                              </globally>
                           </all-paths>
                           <disjunction>
                              <negation>
                                 <conjunction>
                                    <is-fireable>
                                       <transition>deg_ma</transition>
                                    </is-fireable>
                                    <is-fireable>
                                       <transition>transl_r</transition>
                                    </is-fireable>
                                 </conjunction>
                              </negation>
                              <conjunction>
                                 <negation>
                                    <is-fireable>
                                       <transition>deactive</transition>
                                    </is-fireable>
                                 </negation>
                                 <is-fireable>
                                    <transition>deactive</transition>
                                 </is-fireable>
                              </conjunction>
                           </disjunction>
                        </conjunction>
                        <is-fireable>
                           <transition>transc_da</transition>
                        </is-fireable>
                     </conjunction>
                     <is-fireable>
                        <transition>deg_ma</transition>
                     </is-fireable>
                  </conjunction>
               </next>
            </exists-path>
            <negation>
               <all-paths>
                  <next>
                     <negation>
                        <exists-path>
                           <globally>
                              <conjunction>
                                 <all-paths>
                                    <until>
                                       <before>
                                          <is-fireable>
                                             <transition>deg_mr</transition>
                                          </is-fireable>
                                       </before>
                                       <reach>
                                          <is-fireable>
                                             <transition>rel_a</transition>
                                          </is-fireable>
                                       </reach>
                                    </until>
                                 </all-paths>
                                 <conjunction>
                                    <is-fireable>
                                       <transition>transl_r</transition>
                                    </is-fireable>
                                    <is-fireable>
                                       <transition>transl_a</transition>
                                    </is-fireable>
                                 </conjunction>
                              </conjunction>
                           </globally>
                        </exists-path>
                     </negation>
                  </next>
               </all-paths>
            </negation>
         </disjunction>
      </formula>
   </property>
   <property>
      <id>CircadianClock-PT-000001-CTLFireability-11</id>
      <description>Automatically generated by Citili v2022</description>
      <formula>
         <exists-path>
            <until>
               <before>
                  <all-paths>
                     <globally>
                        <exists-path>
                           <next>
                              <negation>
                                 <conjunction>
                                    <negation>
                                       <is-fireable>
                                          <transition>transc_dr</transition>
                                       </is-fireable>
                                    </negation>
                                    <all-paths>
                                       <next>
                                          <is-fireable>
                                             <transition>transc_dr</transition>
                                          </is-fireable>
                                       </next>
                                    </all-paths>
                                 </conjunction>
                              </negation>
                           </next>
                        </exists-path>
                     </globally>
                  </all-paths>
               </before>
               <reach>
                  <disjunction>
                     <exists-path>
                        <next>
                           <disjunction>
                              <conjunction>
                                 <disjunction>
                                    <is-fireable>
                                       <transition>transc_dr</transition>
                                    </is-fireable>
                                    <conjunction>
                                       <is-fireable>
                                          <transition>rel_a</transition>
                                       </is-fireable>
                                       <is-fireable>
                                          <transition>bind_r</transition>
                                       </is-fireable>
                                    </conjunction>
                                 </disjunction>
                                 <exists-path>
                                    <next>
                                       <is-fireable>
                                          <transition>transc_da</transition>
                                       </is-fireable>
                                    </next>
                                 </exists-path>
                              </conjunction>
                              <conjunction>
                                 <disjunction>
                                    <exists-path>
                                       <next>
                                          <is-fireable>
                                             <transition>deg_a</transition>
                                          </is-fireable>
                                       </next>
                                    </exists-path>
                                    <negation>
                                       <is-fireable>
                                          <transition>bind_a</transition>
                                       </is-fireable>
                                    </negation>
                                 </disjunction>
                                 <all-paths>
                                    <finally>
                                       <is-fireable>
                                          <transition>transc_da</transition>
                                       </is-fireable>
                                    </finally>
                                 </all-paths>
                              </conjunction>
                           </disjunction>
                        </next>
                     </exists-path>
                     <all-paths>
                        <next>
                           <negation>
                              <disjunction>
                                 <conjunction>
                                    <negation>
                                       <is-fireable>
                                          <transition>deg_r</transition>
                                       </is-fireable>
                                    </negation>
                                    <all-paths>
                                       <finally>
                                          <is-fireable>
                                             <transition>rel_r</transition>
                                          </is-fireable>
                                       </finally>
                                    </all-paths>
                                 </conjunction>
                                 <is-fireable>
                                    <transition>transc_dr_a</transition>
                                 </is-fireable>
                              </disjunction>
                           </negation>
                        </next>
                     </all-paths>
                  </disjunction>
               </reach>
            </until>
         </exists-path>
      </formula>
   </property>
   <property>
      <id>CircadianClock-PT-000001-CTLFireability-12</id>
      <description>Automatically generated by Citili v2022</description>
      <formula>
         <conjunction>
            <exists-path>
               <globally>
                  <all-paths>
                     <finally>
                        <is-fireable>
                           <transition>rel_a</transition>
                        </is-fireable>
                     </finally>
                  </all-paths>
               </globally>
            </exists-path>
            <exists-path>
               <until>
                  <before>
                     <all-paths>
                        <globally>
                           <all-paths>
                              <finally>
                                 <negation>
                                    <disjunction>
                                       <is-fireable>
                                          <transition>deg_a</transition>
                                       </is-fireable>
                                       <is-fireable>
                                          <transition>bind_a</transition>
                                       </is-fireable>
                                    </disjunction>
                                 </negation>
                              </finally>
                           </all-paths>
                        </globally>
                     </all-paths>
                  </before>
                  <reach>
                     <disjunction>
                        <all-paths>
                           <until>
                              <before>
                                 <disjunction>
                                    <conjunction>
                                       <is-fireable>
                                          <transition>deg_mr</transition>
                                       </is-fireable>
                                       <is-fireable>
                                          <transition>transc_dr_a</transition>
                                       </is-fireable>
                                    </conjunction>
                                    <disjunction>
                                       <is-fireable>
                                          <transition>transc_dr</transition>
                                       </is-fireable>
                                       <conjunction>
                                          <is-fireable>
                                             <transition>deg_mr</transition>
                                          </is-fireable>
                                          <is-fireable>
                                             <transition>transl_a</transition>
                                          </is-fireable>
                                       </conjunction>
                                    </disjunction>
                                 </disjunction>
                              </before>
                              <reach>
                                 <disjunction>
                                    <all-paths>
                                       <until>
                                          <before>
                                             <is-fireable>
                                                <transition>transc_dr_a</transition>
                                             </is-fireable>
                                          </before>
                                          <reach>
                                             <is-fireable>
                                                <transition>deactive</transition>
                                             </is-fireable>
                                          </reach>
                                       </until>
                                    </all-paths>
                                    <disjunction>
                                       <disjunction>
                                          <is-fireable>
                                             <transition>transc_dr</transition>
                                          </is-fireable>
                                          <is-fireable>
                                             <transition>transc_da</transition>
                                          </is-fireable>
                                       </disjunction>
                                       <negation>
                                          <is-fireable>
                                             <transition>transl_a</transition>
                                          </is-fireable>
                                       </negation>
                                    </disjunction>
                                 </disjunction>
                              </reach>
                           </until>
                        </all-paths>
                        <disjunction>
                           <all-paths>
                              <finally>
                                 <exists-path>
                                    <finally>
                                       <is-fireable>
                                          <transition>transl_a</transition>
                                       </is-fireable>
                                    </finally>
                                 </exists-path>
                              </finally>
                           </all-paths>
                           <disjunction>
                              <conjunction>
                                 <conjunction>
                                    <is-fireable>
                                       <transition>transl_a</transition>
                                    </is-fireable>
                                    <exists-path>
                                       <globally>
                                          <is-fireable>
                                             <transition>deg_r</transition>
                                          </is-fireable>
                                       </globally>
                                    </exists-path>
                                 </conjunction>
                                 <all-paths>
                                    <finally>
                                       <is-fireable>
                                          <transition>transl_a</transition>
                                       </is-fireable>
                                    </finally>
                                 </all-paths>
                              </conjunction>
                              <all-paths>
                                 <globally>
                                    <negation>
                                       <is-fireable>
                                          <transition>bind_r</transition>
                                       </is-fireable>
                                    </negation>
                                 </globally>
                              </all-paths>
                           </disjunction>
                        </disjunction>
                     </disjunction>
                  </reach>
               </until>
            </exists-path>
         </conjunction>
      </formula>
   </property>
   <property>
      <id>CircadianClock-PT-000001-CTLFireability-13</id>
      <description>Automatically generated by Citili v2022</description>
      <formula>
         <conjunction>
            <all-paths>
               <until>
                  <before>
                     <all-paths>
                        <next>
                           <negation>
                              <disjunction>
                                 <is-fireable>
                                    <transition>transc_dr</transition>
                                 </is-fireable>
                                 <is-fireable>
                                    <transition>transc_dr</transition>
                                 </is-fireable>
                              </disjunction>
                           </negation>
                        </next>
                     </all-paths>
                  </before>
                  <reach>
                     <disjunction>
                        <is-fireable>
                           <transition>transl_a</transition>
                        </is-fireable>
                        <disjunction>
                           <exists-path>
                              <globally>
                                 <disjunction>
                                    <conjunction>
                                       <is-fireable>
                                          <transition>rel_a</transition>
                                       </is-fireable>
                                       <is-fireable>
                                          <transition>transc_dr</transition>
                                       </is-fireable>
                                    </conjunction>
                                    <all-paths>
                                       <globally>
                                          <is-fireable>
                                             <transition>deg_mr</transition>
                                          </is-fireable>
                                       </globally>
                                    </all-paths>
                                 </disjunction>
                              </globally>
                           </exists-path>
                           <all-paths>
                              <next>
                                 <conjunction>
                                    <conjunction>
                                       <is-fireable>
                                          <transition>transl_r</transition>
                                       </is-fireable>
                                       <is-fireable>
                                          <transition>rel_r</transition>
                                       </is-fireable>
                                    </conjunction>
                                    <all-paths>
                                       <next>
                                          <is-fireable>
                                             <transition>transc_dr_a</transition>
                                          </is-fireable>
                                       </next>
                                    </all-paths>
                                 </conjunction>
                              </next>
                           </all-paths>
                        </disjunction>
                     </disjunction>
                  </reach>
               </until>
            </all-paths>
            <all-paths>
               <next>
                  <is-fireable>
                     <transition>deg_c</transition>
                  </is-fireable>
               </next>
            </all-paths>
         </conjunction>
      </formula>
   </property>
   <property>
      <id>CircadianClock-PT-000001-CTLFireability-14</id>
      <description>Automatically generated by Citili v2022</description>
      <formula>
         <all-paths>
            <globally>
               <exists-path>
                  <finally>
                     <is-fireable>
                        <transition>transc_da</transition>
                     </is-fireable>
                  </finally>
               </exists-path>
            </globally>
         </all-paths>
      </formula>
   </property>
   <property>
      <id>CircadianClock-PT-000001-CTLFireability-15</id>
      <description>Automatically generated by Citili v2022</description>
      <formula>
         <negation>
            <negation>
               <all-paths>
                  <globally>
                     <exists-path>
                        <until>
                           <before>
                              <disjunction>
                                 <exists-path>
                                    <finally>
                                       <is-fireable>
                                          <transition>bind_r</transition>
                                       </is-fireable>
                                    </finally>
                                 </exists-path>
                                 <conjunction>
                                    <negation>
                                       <is-fireable>
                                          <transition>rel_r</transition>
                                       </is-fireable>
                                    </negation>
                                    <disjunction>
                                       <is-fireable>
                                          <transition>rel_a</transition>
                                       </is-fireable>
                                       <is-fireable>
                                          <transition>transc_dr_a</transition>
                                       </is-fireable>
                                    </disjunction>
                                 </conjunction>
                              </disjunction>
                           </before>
                           <reach>
                              <conjunction>
                                 <negation>
                                    <disjunction>
                                       <is-fireable>
                                          <transition>transc_da_a</transition>
                                       </is-fireable>
                                       <is-fireable>
                                          <transition>transc_da_a</transition>
                                       </is-fireable>
                                    </disjunction>
                                 </negation>
                                 <disjunction>
                                    <exists-path>
                                       <next>
                                          <is-fireable>
                                             <transition>bind_a</transition>
                                          </is-fireable>
                                       </next>
                                    </exists-path>
                                    <all-paths>
                                       <next>
                                          <is-fireable>
                                             <transition>deg_ma</transition>
                                          </is-fireable>
                                       </next>
                                    </all-paths>
                                 </disjunction>
                              </conjunction>
                           </reach>
                        </until>
                     </exists-path>
                  </globally>
               </all-paths>
            </negation>
         </negation>
      </formula>
   </property>
</property-set>
